todoist_conv/__init__.py
todoist_conv/cli.py
todoist_conv/formats/__init__.py
todoist_conv/formats/base.py
todoist_conv/formats/csv/__init__.py
todoist_conv/formats/csv/common.py
todoist_conv/formats/csv/parser.py
todoist_conv/formats/csv/serializer.py
todoist_conv/formats/json.py
todoist_conv/formats/opml/__init__.py
todoist_conv/formats/opml/parser.py
todoist_conv/formats/opml/serializer.py
todoist_conv/model.py
todoist_conv/text.py
todoist_conv-0.1.5.dist-info/METADATA
todoist_conv-0.1.5.dist-info/entry_points.txt
todoist_conv-0.1.5.dist-info/WHEEL
todoist_conv-0.1.5.dist-info/RECORD
